mntm_asset_packer.py
mntm_asset_packer-1.2.1.dist-info/METADATA
mntm_asset_packer-1.2.1.dist-info/WHEEL
mntm_asset_packer-1.2.1.dist-info/entry_points.txt
mntm_asset_packer-1.2.1.dist-info/RECORD
