Metadata-Version: 2.4
Name: mntm-asset-packer
Version: 1.2.1
Summary: An improved asset packer script to make the process of creating and packing asset packs for the Momentum firmware easier.
Author-email: notnotnescap <nescap@tuta.io>
Requires-Python: >=3.10
Requires-Dist: heatshrink2>=0.1.0
Requires-Dist: pillow>=3.4.0
